UzParser/__init__.py
UzParser/lexicon.csv
UzParser/non_affixed_word.csv
UzParser/web-interface-ui.png
UzParser-0.0.9.dist-info/LICENSE
UzParser-0.0.9.dist-info/METADATA
UzParser-0.0.9.dist-info/WHEEL
UzParser-0.0.9.dist-info/top_level.txt
UzParser-0.0.9.dist-info/RECORD
