Metadata-Version: 2.1
Name: UzParser
Version: 0.0.9
Summary: uzparser | Uzbek Syntax Parser on Python
Home-page: https://github.com/MardonaKarimova/uzparser
Author: Mardona Karimova
Author-email: karimovaam@gmail.com
License: UNKNOWN
Project-URL: Bug Tracker, https://github.com/MardonaKarimova/uzparser/issues
Keywords: syntax analysis,parser,uzbek-language,tree,pos tagging,morphological tagging
Platform: UNKNOWN
Classifier: Programming Language :: Python :: 3
Classifier: License :: OSI Approved :: MIT License
Classifier: Operating System :: OS Independent
Requires-Python: >=3.6
License-File: LICENSE
Requires-Dist: UzMorphAnalyser
Requires-Dist: pandas
